{"name":"test002","id":"com.localhost.serviceinfo.ServiceCurdInfo:test002","testCaseName":"com.localhost.serviceinfo.ServiceCurdInfo","userStory":{"id":"com.localhost.serviceinfo.ServiceCurdInfo","storyName":"Service curd info","storyClassName":"com.localhost.serviceinfo.ServiceCurdInfo","path":"com.localhost.serviceinfo","type":"story"},"featureTag":{"name":"Serviceinfo/Service curd info","type":"story"},"title":"This will fath single service","tags":[{"name":"Serviceinfo/Service curd info","type":"story"}],"startTime":"2022-06-07T12:28:59.170+01:00[Europe/London]","duration":1,"projectKey":"","manual":false,"testSource":"JUnit","result":"SUCCESS"}